ansible_dev_environment/__init__.py
ansible_dev_environment/__main__.py
ansible_dev_environment/arg_parser.py
ansible_dev_environment/cli.py
ansible_dev_environment/collection.py
ansible_dev_environment/config.py
ansible_dev_environment/definitions.py
ansible_dev_environment/output.py
ansible_dev_environment/tree.py
ansible_dev_environment/utils.py
ansible_dev_environment/subcommands/__init__.py
ansible_dev_environment/subcommands/checker.py
ansible_dev_environment/subcommands/inspector.py
ansible_dev_environment/subcommands/installer.py
ansible_dev_environment/subcommands/lister.py
ansible_dev_environment/subcommands/treemaker.py
ansible_dev_environment/subcommands/uninstaller.py
ansible_dev_environment-26.1.0.dist-info/licenses/LICENSE
ansible_dev_environment-26.1.0.dist-info/METADATA
ansible_dev_environment-26.1.0.dist-info/WHEEL
ansible_dev_environment-26.1.0.dist-info/entry_points.txt
ansible_dev_environment-26.1.0.dist-info/top_level.txt
ansible_dev_environment-26.1.0.dist-info/RECORD
