Metadata-Version: 2.4
Name: ansible-dev-environment
Version: 26.1.0
Summary: A pip-like ansible collection installer.
Author-email: "Bradley A. Thornton" <bthornto@redhat.com>
Maintainer-email: Ansible by Red Hat <info@ansible.com>
License-Expression: GPL-3.0-only
Project-URL: changelog, https://github.com/ansible/ansible-dev-environment/releases
Project-URL: documentation, https://ansible.readthedocs.io/projects/dev-environment/
Project-URL: homepage, https://github.com/ansible/ansible-dev-environment
Project-URL: repository, https://github.com/ansible/ansible-dev-environment
Keywords: ansible
Classifier: Development Status :: 5 - Production/Stable
Classifier: Intended Audience :: Developers
Classifier: Operating System :: OS Independent
Classifier: Programming Language :: Python :: 3 :: Only
Classifier: Programming Language :: Python :: 3
Classifier: Programming Language :: Python :: 3.10
Classifier: Programming Language :: Python :: 3.11
Classifier: Programming Language :: Python :: 3.12
Classifier: Programming Language :: Python :: 3.13
Classifier: Programming Language :: Python :: Implementation :: CPython
Classifier: Programming Language :: Python
Classifier: Topic :: Software Development
Classifier: Topic :: Utilities
Requires-Python: >=3.10
License-File: LICENSE
Requires-Dist: ansible-builder>=3.1.0
Requires-Dist: bindep>=2.13.0
Requires-Dist: pyyaml>=6.0.1
Requires-Dist: subprocess-tee>=0.4.2
Dynamic: license-file
